auth3/__init__.py
auth3/identity/__init__.py
auth3/identity/admin/__init__.py
auth3/identity/admin/admin_pb2.py
auth3/identity/admin/admin_pb2_grpc.py
auth3-1.0.1.dist-info/LICENSE
auth3-1.0.1.dist-info/METADATA
auth3-1.0.1.dist-info/WHEEL
auth3-1.0.1.dist-info/top_level.txt
auth3-1.0.1.dist-info/RECORD
