Metadata-Version: 2.1
Name: auth3
Version: 1.0.1
Summary: Official SDK to use the Auth3.dev Identity Platform API
Home-page: https://auth3.dev/
Author: Auth3.dev
License: Apache-2.0
Project-URL: Bug Tracker, https://github.com/auth3-dev/python-sdk/issues
Platform: UNKNOWN
License-File: LICENSE
Requires-Dist: grpcio (>=1.37.1)
Requires-Dist: protobuf
